moirepy/__init__.py
moirepy/layers.py
moirepy/moire.py
moirepy/utils.py
moirepy-0.0.8.dist-info/licenses/LICENSE
moirepy-0.0.8.dist-info/METADATA
moirepy-0.0.8.dist-info/WHEEL
moirepy-0.0.8.dist-info/top_level.txt
moirepy-0.0.8.dist-info/RECORD
