Metadata-Version: 2.4
Name: moirepy
Version: 0.0.8
Summary: Simulate moire lattice systems in both real and momentum space and calculate various related observables.
Home-page: https://github.com/jabed-umar/MoirePy
Author: Aritra Mukhopadhyay, Jabed Umar
Author-email: amukherjeeniser@gmail.com, jabedumar12@gmail.com
License: MIT
Project-URL: Documentation, https://jabed-umar.github.io/MoirePy/
Project-URL: Source Code, https://github.com/jabed-umar/MoirePy
Project-URL: Bug Tracker, https://github.com/jabed-umar/MoirePy/issues
Keywords: python,moire,moiré,moire lattice,twistronics,bilayer graphene,tight binding,lattice simulation,physics,material science,condensed matter,k-space,real-space
Classifier: Development Status :: 4 - Beta
Classifier: Intended Audience :: Education
Classifier: Intended Audience :: Science/Research
Classifier: License :: OSI Approved :: MIT License
Classifier: Operating System :: OS Independent
Classifier: Programming Language :: Python
Classifier: Programming Language :: Python :: 3
Classifier: Programming Language :: Python :: 3.7
Classifier: Programming Language :: Python :: 3.8
Classifier: Programming Language :: Python :: 3.9
Classifier: Programming Language :: Python :: 3.10
Classifier: Programming Language :: Python :: 3.11
Classifier: Programming Language :: Python :: 3.12
Classifier: Topic :: Education
Classifier: Topic :: Scientific/Engineering
Classifier: Topic :: Scientific/Engineering :: Chemistry
Classifier: Topic :: Scientific/Engineering :: Mathematics
Classifier: Topic :: Scientific/Engineering :: Physics
Requires-Python: >=3.7
License-File: LICENSE
Requires-Dist: numpy
Requires-Dist: scipy
Requires-Dist: matplotlib
Requires-Dist: tqdm
Dynamic: author
Dynamic: author-email
Dynamic: classifier
Dynamic: description
Dynamic: description-content-type
Dynamic: home-page
Dynamic: keywords
Dynamic: license
Dynamic: license-file
Dynamic: project-url
Dynamic: requires-dist
Dynamic: requires-python
Dynamic: summary
